new/__init__.py
new/__main__.py
new/replace.py
new/repo.py
new/template.py
tests/__init__.py
tests/replace_test.py
tests/repo_test.py
tests/template_test.py
new_project-0.5.5.dist-info/METADATA
new_project-0.5.5.dist-info/WHEEL
new_project-0.5.5.dist-info/entry_points.txt
new_project-0.5.5.dist-info/top_level.txt
new_project-0.5.5.dist-info/RECORD
