Metadata-Version: 2.1
Name: new-project
Version: 0.5.5
Summary: Generate new projects from git repositories
Home-page: https://github.com/divanvisagie/new
Author: Divan Visagie
Author-email: me@dvisagie.com
License: UNKNOWN
Platform: UNKNOWN
Classifier: Programming Language :: Python :: 3
Classifier: License :: OSI Approved :: MIT License
Classifier: Operating System :: OS Independent
Requires-Python: >=3.6
Requires-Dist: PyYAML
